catcoder_cli/__init__.py
catcoder_cli/cli.py
catcoder_cli/solve.py
catcoder_cli-0.1.1.dist-info/METADATA
catcoder_cli-0.1.1.dist-info/WHEEL
catcoder_cli-0.1.1.dist-info/entry_points.txt
catcoder_cli-0.1.1.dist-info/top_level.txt
catcoder_cli-0.1.1.dist-info/RECORD
