Metadata-Version: 2.2
Name: catcoder-cli
Version: 0.1.1
Summary: A CLI for the Cloudflight Coding Contest
Requires-Python: >=3.13
Requires-Dist: colorama>=0.4.6
Requires-Dist: platformdirs>=4.3.6
Requires-Dist: requests>=2.32.3
